<?xml version="1.0" encoding="UTF-8"?>
<!DOCTYPE hibernate-mapping PUBLIC 
	"-//Hibernate/Hibernate Mapping DTD 3.0//EN"
	"http://www.hibernate.org/dtd/hibernate-mapping-3.0.dtd">
<hibernate-mapping package="Tree.po">
	<class name="Kzblxdmb" table="kzblxdmb">
		<id name="id" type="integer" column="id">
			<generator class="increment"/>
		</id> 
		<property name="code" column="code" type="string" not-null="true"/>
		<property name="name" column="name" type="string" not-null="true"/>    
		<property name="defination" column="defination" type="text"></property>
		<property name="level" column="level" type="int"></property> 
	</class>
</hibernate-mapping>